README.md
demeter.py
setup.py
python_demeter.egg-info/PKG-INFO
python_demeter.egg-info/SOURCES.txt
python_demeter.egg-info/dependency_links.txt
python_demeter.egg-info/requires.txt
python_demeter.egg-info/top_level.txt