Metadata-Version: 1.0
Name: python-demeter
Version: 0.2.0
Summary: Extremely limited library for downloading from and uploading files to Google Drive.
Home-page: https://github.com/jerome-montino/demeter
Author: Jerome Montino
Author-email: jerome.montino@gmail.com
License: MIT
Platform: UNKNOWN
